{
  "$schema": "Campi boe regionali Sardegna — PRRPT 2024",
  "generated": "2026-05-06",
  "source": "PRRPT 2024 — Piano Regionale della Rete della Portualità Turistica (rilevamento 2022-23)",
  "verified_by": "Documento ufficiale Regione Sardegna + ricerche puntuali coordinate",
  "scope": "Campi boe Sardegna in concessione demaniale marittima regionale (D.G.R. 28/45/2011, durata max 6 anni)",
  "stats": {
    "total_buoy_fields": 14,
    "total_posts": 459,
    "totale_posti_barca_sardegna": 28000,
    "campi_boe_pct": "1.8%",
    "note": "Esclude AMP Tavolara (35 posti, in fase progetto - vedi amp-it.json) — totale PRRPT 15 campi/494 posti includendo Tavolara"
  },
  "buoyFields": [
    {
      "id": "sa-porto-raphael",
      "name": "Porto Raphael",
      "country": "Italia",
      "flag": "IT",
      "type": "mooring",
      "subtype": "regional_concession",
      "status": "operative",
      "region": "Sardegna",
      "quadrant": "NE (Gallura)",
      "comune": "Palau",
      "lat": 41.1980,
      "lon": 9.3880,
      "capacity": {"total": 32, "breakdown": "32 posti — concessione demaniale regionale", "since": null},
      "manager": {"name": "Concessione privata - area Porto Rafael, Palau", "type": "regional_concession", "website": null},
      "notes": "Estremo nord Palau, Cala Inglese (\"piscina di Porto Rafael\"). Vista Arcipelago La Maddalena. Frequentato da vip e velisti.",
      "sources": ["PRRPT 2024 Regione Sardegna", "https://palauturismo.com/"]
    },
    {
      "id": "sa-mare-azzurro",
      "name": "Campo Ormeggio Mare Azzurro Snc",
      "country": "Italia",
      "flag": "IT",
      "type": "mooring",
      "subtype": "regional_concession",
      "status": "operative",
      "region": "Sardegna",
      "quadrant": "NE (Gallura)",
      "comune": "Olbia",
      "lat": 40.8520,
      "lon": 9.6600,
      "capacity": {"total": 55, "breakdown": "55 posti — Mare Azzurro Snc (concessionario privato)", "since": null},
      "manager": {
        "name": "Mare Azzurro Snc",
        "type": "private",
        "website": "https://www.mare-azzurro.net/",
        "address": "Loc. Santa Giusta, 07026 Loiri Porto San Paolo (sede)"
      },
      "notes": "Area Porto Istana, AMP Tavolara - Punta Coda Cavallo. Diving + noleggio + ormeggi. Fondata 1986 da Tonino e Ottavio Bua.",
      "sources": ["PRRPT 2024", "https://www.mare-azzurro.net/"]
    },
    {
      "id": "sa-tavolara-spalmatore",
      "name": "Tavolara Spalmatore",
      "country": "Italia",
      "flag": "IT",
      "type": "mooring",
      "subtype": "regional_concession",
      "status": "operative",
      "region": "Sardegna",
      "quadrant": "NE (Gallura)",
      "comune": "Olbia",
      "lat": 40.8928,
      "lon": 9.6786,
      "capacity": {"total": 40, "breakdown": "40 posti — campo Spalmatore di Terra (NW isola Tavolara). Distinto dal campo AMP Tavolara (Cala Cavallo, in progetto).", "since": null},
      "manager": {"name": "Concessione regionale", "type": "regional_concession", "website": null},
      "notes": "Spalmatore di Terra, lato NW isola Tavolara. Coordinate da SardegnaNatura (40°53'34\"N 9°40'43\"E). AMP Tavolara - Punta Coda Cavallo.",
      "sources": ["PRRPT 2024", "https://www.sardegnanatura.com/esplora-la-sardegna/spiagge-sardegna/1158-spiaggia-dello-spalmatore-olbia.html"]
    },
    {
      "id": "sa-cala-finanza",
      "name": "Cala Finanza",
      "country": "Italia",
      "flag": "IT",
      "type": "mooring",
      "subtype": "regional_concession",
      "status": "operative",
      "region": "Sardegna",
      "quadrant": "NE (Gallura)",
      "comune": "Loiri di Porto San Paolo",
      "lat": 40.9400,
      "lon": 9.6600,
      "capacity": {"total": 8, "breakdown": "8 posti — campo boe Cala Finanza", "since": null},
      "manager": {"name": "Concessione regionale", "type": "regional_concession"},
      "notes": "Località Cala Finanza SNC, SS125 Orientale Sarda. Spiaggia 65m. Vicino AMP Tavolara.",
      "sources": ["PRRPT 2024"]
    },
    {
      "id": "sa-azzurro-porto-taverna",
      "name": "Azzurro Porto Taverna",
      "country": "Italia",
      "flag": "IT",
      "type": "mooring",
      "subtype": "regional_concession",
      "status": "operative",
      "region": "Sardegna",
      "quadrant": "NE (Gallura)",
      "comune": "Loiri di Porto San Paolo",
      "lat": 40.8583,
      "lon": 9.6542,
      "capacity": {"total": 27, "breakdown": "27 posti — Porto Taverna", "since": null},
      "manager": {"name": "Concessione regionale", "type": "regional_concession"},
      "notes": "Coordinate ufficiali SardegnaNatura: 40°51'30\"N 9°39'15\"E. AMP Tavolara - Punta Coda Cavallo.",
      "sources": ["PRRPT 2024", "https://www.sardegnanatura.com/esplora-la-sardegna/spiagge-sardegna/1161-spiaggia-di-porto-taverna-loiri-porto-san-paolo.html"]
    },
    {
      "id": "sa-cala-suaraccia",
      "name": "Cala Suaraccia (Le Farfalle)",
      "country": "Italia",
      "flag": "IT",
      "type": "mooring",
      "subtype": "regional_concession",
      "status": "operative",
      "region": "Sardegna",
      "quadrant": "NE (Gallura)",
      "comune": "San Teodoro",
      "lat": 40.8411,
      "lon": 9.7057,
      "capacity": {"total": 13, "breakdown": "13 posti", "since": null},
      "manager": {"name": "Concessione regionale", "type": "regional_concession"},
      "notes": "Coordinate verificate: 40°50'28\"N 9°42'20.5\"E. Anche \"Spiaggia delle Farfalle\". Promontorio Capo Coda Cavallo, AMP Tavolara.",
      "sources": ["PRRPT 2024", "https://www.sardegnanatura.com/esplora-la-sardegna/spiagge-sardegna/1319-spiaggia-le-farfalle-cala-suaraccia-san-teodoro.html"]
    },
    {
      "id": "sa-saline-bamba",
      "name": "Saline Bamba (Salinedda)",
      "country": "Italia",
      "flag": "IT",
      "type": "mooring",
      "subtype": "regional_concession",
      "status": "operative",
      "region": "Sardegna",
      "quadrant": "NE (Gallura)",
      "comune": "San Teodoro",
      "lat": 40.7850,
      "lon": 9.6850,
      "capacity": {"total": 10, "breakdown": "10 posti — Salina Bamba / Salinedda", "since": null},
      "manager": {"name": "Concessione regionale", "type": "regional_concession"},
      "notes": "Sabbia bianca fine, area umida retrostante. Accessibile da SS125 dir. San Teodoro-Olbia, svolta dx incrocio Lutturai. AMP Tavolara.",
      "sources": ["PRRPT 2024", "https://santeodoroturismo.it/territorio-2/spiagge/salina-bamba-e-salinedda/"]
    },
    {
      "id": "sa-cala-gonone",
      "name": "Cala Gonone",
      "country": "Italia",
      "flag": "IT",
      "type": "mooring",
      "subtype": "regional_concession",
      "status": "operative",
      "region": "Sardegna",
      "quadrant": "Centro-Est (Ogliastra/Nuoro)",
      "comune": "Dorgali",
      "lat": 40.2833,
      "lon": 9.6333,
      "capacity": {"total": 100, "breakdown": "100 posti — il più grande campo boe sardo nel PRRPT 2024", "since": null},
      "manager": {"name": "Concessione regionale", "type": "regional_concession"},
      "notes": "Campo boe più grande dei 15 censiti PRRPT 2024. Lead commerciale top per Sardegna centro-orientale. Costa Golfo di Orosei.",
      "sources": ["PRRPT 2024"]
    },
    {
      "id": "sa-baia-sparlotta",
      "name": "Baia della Sparlotta",
      "country": "Italia",
      "flag": "IT",
      "type": "mooring",
      "subtype": "regional_concession",
      "status": "operative",
      "region": "Sardegna",
      "quadrant": "SW (Sulcis)",
      "comune": "Sarroch",
      "lat": 39.0500,
      "lon": 9.0167,
      "capacity": {"total": 20, "breakdown": "20 posti", "since": null},
      "manager": {"name": "Concessione regionale", "type": "regional_concession"},
      "notes": "Costa Sarroch (Sud Cagliari). Coordinate stimate — verifica puntuale consigliata.",
      "sources": ["PRRPT 2024"]
    },
    {
      "id": "sa-capo-malfatano",
      "name": "Capo Malfatano",
      "country": "Italia",
      "flag": "IT",
      "type": "mooring",
      "subtype": "regional_concession",
      "status": "operative",
      "region": "Sardegna",
      "quadrant": "SW (Sulcis)",
      "comune": "Teulada",
      "lat": 38.8710,
      "lon": 8.7760,
      "capacity": {"total": 40, "breakdown": "40 posti — Capo Malfatano", "since": null},
      "manager": {"name": "Concessione regionale", "type": "regional_concession"},
      "notes": "Promontorio tra Tuerredda e Piscinnì. Storico approdo fenicio-punico (VI sec a.C.). Tesoro costiero di Teulada.",
      "sources": ["PRRPT 2024", "https://www.sardegnaturismo.it/it/esplora/capo-malfatano"]
    },
    {
      "id": "sa-porto-tramatzu",
      "name": "Porto Tramatzu",
      "country": "Italia",
      "flag": "IT",
      "type": "mooring",
      "subtype": "regional_concession",
      "status": "operative",
      "region": "Sardegna",
      "quadrant": "SW (Sulcis)",
      "comune": "Teulada",
      "lat": 38.8790,
      "lon": 8.7520,
      "capacity": {"total": 80, "breakdown": "80 posti — secondo campo più grande PRRPT 2024", "since": null},
      "manager": {"name": "Concessione regionale", "type": "regional_concession"},
      "notes": "Promontorio Capo Teulada, SW Sardegna. Spiaggia 300m. Davanti \"Isola Rossa\" (~1km). Lead commerciale top per Sardegna SW.",
      "sources": ["PRRPT 2024", "https://www.sardegnaturismo.it/it/esplora/porto-tramatzu"]
    },
    {
      "id": "sa-punta-saliga",
      "name": "Punta 'e S'Aliga",
      "country": "Italia",
      "flag": "IT",
      "type": "mooring",
      "subtype": "regional_concession",
      "status": "operative",
      "region": "Sardegna",
      "quadrant": "SW (Sulcis)",
      "comune": "Portoscuso",
      "lat": 39.2110,
      "lon": 8.3850,
      "capacity": {"total": 10, "breakdown": "10 posti", "since": null},
      "manager": {"name": "Concessione regionale", "type": "regional_concession"},
      "notes": "Penisola lato ovest stagno Bau Cerbus (Riserva Naturale). Sabbia bianca fine, fossili (oyster shells). Spot kitesurf.",
      "sources": ["PRRPT 2024", "https://www.comune.portoscuso.ci.it/it/vivere-portoscuso/spiagge-e-coste/spiaggia-sa-punta-de-saliga"]
    },
    {
      "id": "sa-bruncu-teula",
      "name": "Bruncu Teula",
      "country": "Italia",
      "flag": "IT",
      "type": "mooring",
      "subtype": "regional_concession",
      "status": "operative",
      "region": "Sardegna",
      "quadrant": "SW (Sulcis)",
      "comune": "San Giovanni Suergiu",
      "lat": 39.0670,
      "lon": 8.4280,
      "capacity": {"total": 20, "breakdown": "20 posti — Bruncu Teula", "since": null},
      "manager": {"name": "Concessione regionale", "type": "regional_concession"},
      "notes": "Villaggio costiero Sulcis, amministrazione divisa fra Portoscuso e San Giovanni Suergiu. Spiaggia 100m, sabbia beige-grigiastra. Riparata dai venti, base pescatori locali.",
      "sources": ["PRRPT 2024", "https://it.wikipedia.org/wiki/Bruncuteula"]
    },
    {
      "id": "sa-masua",
      "name": "Masua",
      "country": "Italia",
      "flag": "IT",
      "type": "mooring",
      "subtype": "regional_concession",
      "status": "operative",
      "region": "Sardegna",
      "quadrant": "SW (Iglesiente)",
      "comune": "Iglesias",
      "lat": 39.3180,
      "lon": 8.4340,
      "capacity": {"total": 4, "breakdown": "4 posti — il più piccolo PRRPT 2024", "since": null},
      "manager": {"name": "Concessione regionale", "type": "regional_concession"},
      "notes": "Frazione di Iglesias, vicino Pan di Zucchero (faraglione 133m). Sabbia dorata medio-grano, mare cristallino, fondali bassi. Sito FAI.",
      "sources": ["PRRPT 2024", "https://www.sardegnaturismo.it/it/esplora/pan-di-zucchero-e-faraglioni-di-masua"]
    }
  ]
}
